SDTcloud/__init__.py
SDTcloud/cassandra_utils.py
SDTcloud/enums.py
SDTcloud/sdtcloud.py
SDTcloud-1.1.56.dist-info/METADATA
SDTcloud-1.1.56.dist-info/WHEEL
SDTcloud-1.1.56.dist-info/top_level.txt
SDTcloud-1.1.56.dist-info/RECORD
