Metadata-Version: 2.1
Name: SDTcloud
Version: 1.1.56
Summary: SDT cloud API Package
Home-page: https://github.com/pypa/sampleproject
Author: sujune
Author-email: sujunelee@sdt.inc
Classifier: Programming Language :: Python :: 3
Classifier: License :: OSI Approved :: MIT License
Classifier: Operating System :: OS Independent
Requires-Python: >=3.6
